geosight/__init__.py
geosight/geosight.py
geosight/geosight_pyspark.py
geosight-0.1.5.dist-info/licenses/LICENSE
geosight-0.1.5.dist-info/METADATA
geosight-0.1.5.dist-info/WHEEL
geosight-0.1.5.dist-info/top_level.txt
geosight-0.1.5.dist-info/RECORD
