Metadata-Version: 2.4
Name: geosight
Version: 0.1.5
Summary: Custom Grid with Pyspark Functions
Author: Abdullah Ghifari
Classifier: Programming Language :: Python :: 3
Classifier: License :: OSI Approved :: MIT License
Classifier: Operating System :: OS Independent
Requires-Python: >=3.7
License-File: LICENSE
Requires-Dist: python-geohash==0.8.5
Requires-Dist: h3==3.7.7
Dynamic: license-file
